qualibrate_runner/__init__.py
qualibrate_runner/__main__.py
qualibrate_runner/api/__init__.py
qualibrate_runner/api/dependencies.py
qualibrate_runner/api/middleware/__init__.py
qualibrate_runner/api/middleware/process_time.py
qualibrate_runner/api/routes/__init__.py
qualibrate_runner/api/routes/get_runnables.py
qualibrate_runner/api/routes/last_run.py
qualibrate_runner/api/routes/others.py
qualibrate_runner/api/routes/submit.py
qualibrate_runner/api/sockets/__init__.py
qualibrate_runner/api/sockets/common.py
qualibrate_runner/api/sockets/tasks.py
qualibrate_runner/api/utils.py
qualibrate_runner/app.py
qualibrate_runner/cli/__init__.py
qualibrate_runner/cli/start.py
qualibrate_runner/config/__init__.py
qualibrate_runner/config/models.py
qualibrate_runner/config/resolvers.py
qualibrate_runner/config/vars.py
qualibrate_runner/core/__init__.py
qualibrate_runner/core/app/__init__.py
qualibrate_runner/core/app/lifespan.py
qualibrate_runner/core/app/periodic_tasks.py
qualibrate_runner/core/app/ws_manager.py
qualibrate_runner/core/app/ws_managers.py
qualibrate_runner/core/models/__init__.py
qualibrate_runner/core/models/active_run.py
qualibrate_runner/core/models/common.py
qualibrate_runner/core/models/enums.py
qualibrate_runner/core/models/last_run.py
qualibrate_runner/core/models/run_results.py
qualibrate_runner/core/models/runner_meta.py
qualibrate_runner/core/models/workflow.py
qualibrate_runner/core/run_job.py
qualibrate_runner/core/statuses.py
qualibrate_runner/core/types.py
qualibrate_runner/py.typed
qualibrate_runner/utils/__init__.py
qualibrate_runner/utils/calibration_nodes_resolver.py
qualibrate_runner/utils/logs_parser.py
qualibrate_runner-0.6.0.dist-info/METADATA
qualibrate_runner-0.6.0.dist-info/WHEEL
qualibrate_runner-0.6.0.dist-info/entry_points.txt
qualibrate_runner-0.6.0.dist-info/licenses/LICENSE
qualibrate_runner-0.6.0.dist-info/RECORD
